src/__init__.py
src/in2xl.py
in2xl-0.1.1.dist-info/LICENSE.txt
in2xl-0.1.1.dist-info/METADATA
in2xl-0.1.1.dist-info/WHEEL
in2xl-0.1.1.dist-info/top_level.txt
in2xl-0.1.1.dist-info/RECORD
