Metadata-Version: 2.1
Name: in2xl
Version: 0.1.1
Summary: A package that allows to insert data in an XLSX file without changing the layout.
Home-page: https://github.com/gozred/python-in2xl
Author: Herzog(gozred)
License: MIT License
Keywords: python,xlsx,excel,dataframe,insert in excel,template,excel template
Platform: UNKNOWN
Classifier: Development Status :: 4 - Beta
Classifier: Intended Audience :: Developers
Classifier: Programming Language :: Python :: 3
Classifier: Operating System :: Unix
Classifier: Operating System :: MacOS :: MacOS X
Classifier: Operating System :: Microsoft :: Windows
License-File: LICENSE.txt
Requires-Dist: openpyxl
Requires-Dist: xlsxwriter
Requires-Dist: ruamel.std.zipfile
Requires-Dist: lxml
Requires-Dist: pandas
